[
  {
    "date": "2025-10-01",
    "basedOn": [
      "06",
      "50",
      "36"
    ],
    "betAmount": 10,
    "om": {
      "numbers": [
        "39",
        "05",
        "37",
        "24",
        "42",
        "93",
        "73",
        "48",
        "58",
        "44",
        "06",
        "84",
        "85",
        "60",
        "46",
        "64",
        "15",
        "94",
        "49",
        "51",
        "28",
        "59",
        "95",
        "00",
        "04",
        "40",
        "82",
        "19",
        "91",
        "55"
      ]
    },
    "danh": {
      "numbers": [
        "36",
        "16",
        "63",
        "72",
        "27",
        "34",
        "61",
        "32",
        "43",
        "23",
        "18",
        "26",
        "12",
        "76",
        "10",
        "62",
        "98",
        "70",
        "78",
        "07",
        "52",
        "81",
        "25",
        "67",
        "21",
        "90",
        "09",
        "89",
        "01",
        "66",
        "87",
        "38",
        "35",
        "54",
        "45",
        "56",
        "53",
        "86",
        "68",
        "65",
        "83",
        "30",
        "31",
        "13",
        "17",
        "33",
        "96",
        "03",
        "77",
        "71",
        "22",
        "99",
        "08",
        "69",
        "80",
        "57",
        "97",
        "79",
        "75",
        "02",
        "20",
        "14",
        "88",
        "92",
        "29",
        "74",
        "47",
        "11",
        "41",
        "50"
      ]
    }
  }
]